ylz_utils/__init__.py
ylz_utils/config.py
ylz_utils/crypto.py
ylz_utils/data.py
ylz_utils/file.py
ylz_utils/image.py
ylz_utils/loger.py
ylz_utils/playwright.py
ylz_utils/soup.py
ylz_utils/cli/__init__.py
ylz_utils/cli/chat.py
ylz_utils/cli/hooks.py
ylz_utils/cli/init.py
ylz_utils/cli/main.py
ylz_utils/cli/neo4j.py
ylz_utils/cli/rag.py
ylz_utils/cli/serve.py
ylz_utils/cli/set_logger.py
ylz_utils/cli/start.py
ylz_utils/cli/test.py
ylz_utils/cli/custom_service/__init__.py
ylz_utils/cli/custom_service/car_rentals.py
ylz_utils/cli/custom_service/db_init.py
ylz_utils/cli/custom_service/excursions.py
ylz_utils/cli/custom_service/flights.py
ylz_utils/cli/custom_service/graph.py
ylz_utils/cli/custom_service/hotels.py
ylz_utils/cli/custom_service/policies.py
ylz_utils/cli/custom_service/utils.py
ylz_utils/cli/graph/__init__.py
ylz_utils/cli/graph/db_graph/__init__.py
ylz_utils/cli/graph/engineer_graph/__init__.py
ylz_utils/cli/graph/engineer_graph/check.py
ylz_utils/cli/graph/engineer_graph/critique.py
ylz_utils/cli/graph/engineer_graph/draft.py
ylz_utils/cli/graph/engineer_graph/gather_requirements.py
ylz_utils/cli/graph/engineer_graph/llm.py
ylz_utils/cli/graph/engineer_graph/loader.py
ylz_utils/cli/graph/engineer_graph/state.py
ylz_utils/cli/graph/life_graph/__init__.py
ylz_utils/cli/graph/life_graph/agent_node.py
ylz_utils/cli/graph/life_graph/life_node.py
ylz_utils/cli/graph/life_graph/life_query_node.py
ylz_utils/cli/graph/life_graph/node.py
ylz_utils/cli/graph/life_graph/state.py
ylz_utils/cli/graph/life_graph/tag_node.py
ylz_utils/cli/graph/public_graph/summary/__init__.py
ylz_utils/cli/graph/public_graph/summary/state.py
ylz_utils/cli/graph/self_rag_graph/__init__.py
ylz_utils/cli/graph/self_rag_graph/edge_decide_to_generate.py
ylz_utils/cli/graph/self_rag_graph/edge_grade_generation_v_documents_and_question.py
ylz_utils/cli/graph/self_rag_graph/node_generate.py
ylz_utils/cli/graph/self_rag_graph/node_grade_documents.py
ylz_utils-0.5.0.dist-info/METADATA
ylz_utils-0.5.0.dist-info/WHEEL
ylz_utils-0.5.0.dist-info/entry_points.txt
ylz_utils-0.5.0.dist-info/top_level.txt
ylz_utils-0.5.0.dist-info/RECORD
